setup.cfg
setup.py
easy_german/__init__.py
easy_german/drive.py
easy_german/settings.py
easy_german/transcripts.py
easy_german/utils.py
easy_german/videos.py
easygerman.egg-info/PKG-INFO
easygerman.egg-info/SOURCES.txt
easygerman.egg-info/dependency_links.txt
easygerman.egg-info/requires.txt
easygerman.egg-info/top_level.txt