Metadata-Version: 1.0
Name: easygerman
Version: 0.2.1
Summary: Download Easy German videos and transcripts
Home-page: https://github.com/family-guy/easy-german
Author: Guy King
Author-email: guy@zorncapital.com
License: UNKNOWN
Platform: UNKNOWN
